subscriptions_to_csv/__init__.py
subscriptions_to_csv/cli.py
subscriptions_to_csv/converter.py
subscriptions_to_csv-2.1.0.dist-info/METADATA
subscriptions_to_csv-2.1.0.dist-info/WHEEL
subscriptions_to_csv-2.1.0.dist-info/entry_points.txt
subscriptions_to_csv-2.1.0.dist-info/top_level.txt
subscriptions_to_csv-2.1.0.dist-info/RECORD
